corespace/__init__.py
corespace/main.py
corespace-0.1.4.2.dist-info/LICENSE
corespace-0.1.4.2.dist-info/METADATA
corespace-0.1.4.2.dist-info/WHEEL
corespace-0.1.4.2.dist-info/top_level.txt
corespace-0.1.4.2.dist-info/RECORD
