Metadata-Version: 2.1
Name: corespace
Version: 0.1.4.2
Summary: Greg Henry open space toolbox
Home-page: https://github.com/GregoireHENRY
Author: Greg Henry
Author-email: gregoire.henry@ipsa.fr
License: UNKNOWN
Platform: UNKNOWN
Classifier: Programming Language :: Python :: 3
Classifier: License :: OSI Approved :: MIT License
Classifier: Operating System :: OS Independent
Requires-Python: >=3.6
